iptables_exporter/__init__.py
iptables_exporter/main.py
iptables_exporter-0.9.3.data/scripts/iptables-exporter
iptables_exporter-0.9.3.dist-info/METADATA
iptables_exporter-0.9.3.dist-info/WHEEL
iptables_exporter-0.9.3.dist-info/top_level.txt
iptables_exporter-0.9.3.dist-info/RECORD
