Metadata-Version: 2.1
Name: iptables-exporter
Version: 0.9.3
Summary: Prometheus iptables exporter
Home-page: https://github.com/madron/iptables-exporter
Author: Massimiliano Ravelli
Author-email: massimiliano.ravelli@gmail.com
License: MIT
Keywords: prometheus monitoring iptables bandwidth
Platform: UNKNOWN
Classifier: Development Status :: 3 - Alpha
Classifier: Environment :: Console
Classifier: Intended Audience :: System Administrators
Classifier: Topic :: System :: Monitoring
Classifier: License :: OSI Approved :: MIT License
Classifier: Programming Language :: Python :: 3
Classifier: Programming Language :: Python :: 3.4
Classifier: Programming Language :: Python :: 3.5
Classifier: Programming Language :: Python :: 3.6
Classifier: Programming Language :: Python :: 3.7
Requires-Dist: prometheus-client
Requires-Dist: python-iptables (>=0.13)
